{
  "minecraft:recipes/decorations/snow": {
    "criteria": {
      "has_snowball": "2022-02-15 05:24:52 +0000"
    },
    "done": true
  },
  "minecraft:recipes/misc/iron_nugget_from_blasting": {
    "criteria": {
      "has_chainmail_helmet": "2022-03-05 02:18:17 +0000"
    },
    "done": true
  },
  "minecraft:recipes/redstone/dispenser": {
    "criteria": {
      "has_bow": "2022-02-15 05:22:17 +0000"
    },
    "done": true
  },
  "minecraft:adventure/ol_betsy": {
    "criteria": {
      "shot_crossbow": "2022-02-15 05:42:29 +0000"
    },
    "done": true
  },
  "minecraft:adventure/root": {
    "criteria": {
      "killed_something": "2022-02-15 05:22:43 +0000"
    },
    "done": true
  },
  "minecraft:adventure/kill_a_mob": {
    "criteria": {
      "minecraft:creeper": "2022-02-15 05:28:13 +0000"
    },
    "done": true
  },
  "minecraft:adventure/kill_all_mobs": {
    "criteria": {
      "minecraft:magma_cube": "2022-02-15 05:56:38 +0000",
      "minecraft:creeper": "2022-02-15 05:28:13 +0000",
      "minecraft:slime": "2022-02-15 06:02:47 +0000"
    },
    "done": false
  },
  "minecraft:adventure/shoot_arrow": {
    "criteria": {
      "shot_arrow": "2022-02-15 05:22:43 +0000"
    },
    "done": true
  },
  "minecraft:recipes/building_blocks/snow_block": {
    "criteria": {
      "has_snowball": "2022-02-15 05:24:52 +0000"
    },
    "done": true
  },
  "minecraft:recipes/misc/iron_nugget_from_smelting": {
    "criteria": {
      "has_chainmail_helmet": "2022-03-05 02:18:17 +0000"
    },
    "done": true
  },
  "minecraft:adventure/adventuring_time": {
    "criteria": {
      "minecraft:plains": "2022-02-15 05:22:04 +0000"
    },
    "done": false
  },
  "DataVersion": 2975
}