{"stats":{"minecraft:used":{"minecraft:bow":253,"minecraft:panda_spawn_egg":8,"minecraft:snowball":3},"minecraft:dropped":{"minecraft:bow":143,"minecraft:snowball":2},"minecraft:broken":{"minecraft:chainmail_helmet":5},"minecraft:picked_up":{"minecraft:panda_spawn_egg":8,"minecraft:snowball":5},"minecraft:custom":{"minecraft:time_since_rest":129793,"minecraft:open_chest":22,"minecraft:crouch_one_cm":2195,"minecraft:play_time":129793,"minecraft:sprint_one_cm":617789,"minecraft:walk_one_cm":184461,"minecraft:sneak_time":20554,"minecraft:mob_kills":1,"minecraft:drop":145,"minecraft:damage_dealt_resisted":44140,"minecraft:jump":3125,"minecraft:leave_game":7,"minecraft:time_since_death":129793,"minecraft:climb_one_cm":14030,"minecraft:total_world_time":129793,"minecraft:damage_resisted":3123389,"minecraft:fly_one_cm":870009,"minecraft:fall_one_cm":215455}},"DataVersion":3700}